rtl/alu.sv
// ============================================================
// ALU — Arithmetic Logic Unit
// Supported operations (alu_control encoding):
//   3'b000  ADD
//   3'b001  SUB
//   3'b010  AND
//   3'b011  OR
//   3'b100  XOR  (reserved for future use)
// ============================================================

module alu (
    input  logic [31:0] a,
    input  logic [31:0] b,
    input  logic [2:0]  alu_control,
    output logic [31:0] result
);

    always_comb begin
        case (alu_control)
            3'b000:  result = a + b;        // ADD
            3'b001:  result = a - b;        // SUB
            3'b010:  result = a & b;        // AND
            3'b011:  result = a | b;        // OR
            3'b100:  result = a ^ b;        // XOR
            default: result = 32'b0;
        endcase
    end

endmodule

tb/alu_tb.sv
// ============================================================
// alu_tb.sv — ALU unit testbench
//
// alu_control encoding (must match rtl/alu.sv):
//   3'b000  ADD
//   3'b001  SUB
//   3'b010  AND
//   3'b011  OR
//   3'b100  XOR
//
// Each test prints:
//   TEST <name>
//   Expected result = <value>
//   Actual   result = <value>
//   PASS / FAIL
// ============================================================

`timescale 1ns/1ps

module alu_tb;

    logic [31:0] a;
    logic [31:0] b;
    logic [2:0]  alu_control;
    logic [31:0] result;

    int pass_count;
    int fail_count;

    alu dut (
        .a          (a),
        .b          (b),
        .alu_control(alu_control),
        .result     (result)
    );

    // Self-checking task
    task automatic check(
        input string   op_name,
        input logic [31:0] a_in,
        input logic [31:0] b_in,
        input logic [2:0]  ctrl,
        input int          expected
    );
        int actual;
        a           = a_in;
        b           = b_in;
        alu_control = ctrl;
        #1; // allow combinational propagation
        actual = int'(result);
        $display("TEST  %s", op_name);
        $display("  Expected  result = %0d", expected);
        $display("  Actual    result = %0d", actual);
        if (actual === expected) begin
            $display("  --> PASS\n");
            pass_count++;
        end else begin
            $display("  --> FAIL\n");
            fail_count++;
        end
    endtask

    initial begin
        $dumpfile("alu.vcd");
        $dumpvars(0, alu_tb);

        pass_count = 0;
        fail_count = 0;

        $display("");
        $display("==================================");
        $display("  ALU Unit Testbench");
        $display("==================================");
        $display("");

        // ADD: 10 + 20 = 30
        check("ADD  10 + 20",  32'd10, 32'd20, 3'b000, 30);

        // ADD negative: -5 + 3 = -2 (two's complement)
        check("ADD  -5 + 3",   32'hFFFFFFFB, 32'd3, 3'b000, -2);

        // SUB: 20 - 10 = 10
        check("SUB  20 - 10",  32'd20, 32'd10, 3'b001, 10);

        // SUB producing zero (used by BEQ comparison)
        check("SUB  7 - 7 = 0", 32'd7, 32'd7, 3'b001, 0);

        // AND: 0b01010 & 0b10100 = 0
        check("AND  10 & 20",   32'd10, 32'd20, 3'b010, 0);

        // AND: 0b0101 & 0b0011 = 0b0001 = 1
        check("AND  5 & 3",     32'd5,  32'd3,  3'b010, 1);

        // OR: 0b01010 | 0b10100 = 0b11110 = 30
        check("OR   10 | 20",   32'd10, 32'd20, 3'b011, 30);

        // OR: 5 | 3 = 7
        check("OR   5 | 3",     32'd5,  32'd3,  3'b011, 7);

        // XOR: 5 ^ 3 = 6
        check("XOR  5 ^ 3",     32'd5,  32'd3,  3'b100, 6);

        // XOR with itself = 0
        check("XOR  x ^ x = 0", 32'd42, 32'd42, 3'b100, 0);

        $display("==================================");
        $display("  RESULTS : %0d PASSED,  %0d FAILED", pass_count, fail_count);
        $display("==================================");

        if (fail_count != 0)
            $fatal(1, "ALU testbench FAILED.");

        $finish;
    end

endmodule

alu.vcd
$date
	Mon Aug 17 00:32:16 2026
$end
$version
	Icarus Verilog
$end
$timescale
	1ps
$end
$scope module alu_tb $end
$var wire 32 ! result [31:0] $end
$var reg 32 " a [31:0] $end
$var reg 3 # alu_control [2:0] $end
$var reg 32 $ b [31:0] $end
$var integer 32 % fail_count [31:0] $end
$var integer 32 & pass_count [31:0] $end
$scope module dut $end
$var wire 32 ' a [31:0] $end
$var wire 3 ( alu_control [2:0] $end
$var wire 32 ) b [31:0] $end
$var reg 32 * result [31:0] $end
$upscope $end
$scope task check $end
$upscope $end
$upscope $end
$enddefinitions $end
$comment Show the parameter values. $end
$dumpall
$end
#0
$dumpvars
b11110 *
b10100 )
b0 (
b1010 '
b0 &
b0 %
b10100 $
b0 #
b1010 "
b11110 !
$end
#1000
b11111111111111111111111111111110 !
b11111111111111111111111111111110 *
b11 $
b11 )
b11111111111111111111111111111011 "
b11111111111111111111111111111011 '
b1 &
#2000
b1010 !
b1010 *
b1 #
b1 (
b1010 $
b1010 )
b10100 "
b10100 '
b10 &
#3000
b0 !
b0 *
b111 $
b111 )
b111 "
b111 '
b11 &
#4000
b10 #
b10 (
b10100 $
b10100 )
b1010 "
b1010 '
b100 &
#5000
b1 !
b1 *
b11 $
b11 )
b101 "
b101 '
b101 &
#6000
b11110 !
b11110 *
b11 #
b11 (
b10100 $
b10100 )
b1010 "
b1010 '
b110 &
#7000
b111 !
b111 *
b11 $
b11 )
b101 "
b101 '
b111 &
#8000
b110 !
b110 *
b100 #
b100 (
b1000 &
#9000
b0 !
b0 *
b101010 $
b101010 )
b101010 "
b101010 '
b1001 &
#10000
b1010 &
