rtl/alu.sv
module alu (
    input  logic [31:0] a,
    input  logic [31:0] b,
    input  logic [2:0]  alu_control,
    output logic [31:0] result
);

    always_comb begin
        case (alu_control)

            3'b001: result = a + b;  // ADD
            3'b010: result = a - b;  // SUB
            3'b011: result = a & b;  // AND
            3'b100: result = a | b;  // OR
            3'b101: result = a ^ b;  // XOR (reserved for later)

            default: result = 32'b0;

        endcase
    end

endmodule

rtl/control_unit.sv
module control_unit (
    input  logic [2:0] alu_control,

    output logic       reg_write
);

    always_comb begin

        // Default: don't write to register file
        reg_write = 1'b0;

        // Valid ALU operation
        if (alu_control != 3'b000)
            reg_write = 1'b1;

    end

endmodule

rtl/register_file.sv
module register_file (
    input  logic        clk,
    input  logic        reset,

    input  logic [4:0]  rs1,
    input  logic [4:0]  rs2,

    input  logic [4:0]  rd,
    input  logic [31:0] write_data,
    input  logic        write_enable,

    output logic [31:0] read_data1,
    output logic [31:0] read_data2
);

    // 32 registers, each 32 bits wide
    logic [31:0] registers [0:31];

    integer i;

    // Write operation
    always_ff @(posedge clk) begin

        if (reset) begin

            for (i = 0; i < 32; i = i + 1)
                registers[i] <= 32'b0;

            registers[1] <= 32'd10;
            registers[2] <= 32'd20;

        end
        else if (write_enable && (rd != 5'b00000)) begin

            registers[rd] <= write_data;

        end

    end

    // Read operations
    always_comb begin

        if (rs1 == 5'b00000)
            read_data1 = 32'b0;
        else
            read_data1 = registers[rs1];

        if (rs2 == 5'b00000)
            read_data2 = 32'b0;
        else
            read_data2 = registers[rs2];

    end

endmodule

rtl/decoder.sv
module decoder (
    input  logic [31:0] instruction,

    output logic [4:0]  rs1,
    output logic [4:0]  rs2,
    output logic [4:0]  rd,

    output logic [2:0]  alu_control
);

    logic [6:0] opcode;
    logic [2:0] funct3;
    logic [6:0] funct7;

    // Extract fields from the instruction
    assign opcode = instruction[6:0];
    assign rd     = instruction[11:7];
    assign funct3 = instruction[14:12];
    assign rs1    = instruction[19:15];
    assign rs2    = instruction[24:20];
    assign funct7 = instruction[31:25];

    // Decode the instruction
    always_comb begin

        // Default: no operation
        alu_control = 3'b000;

        // R-type instruction
        if (opcode == 7'b0110011) begin

            // ADD / SUB
            if (funct3 == 3'b000) begin

                if (funct7 == 7'b0000000)
                    alu_control = 3'b001; // ADD

                else if (funct7 == 7'b0100000)
                    alu_control = 3'b010; // SUB

            end

            // AND
            else if (funct3 == 3'b111)
                alu_control = 3'b011;

            // OR
            else if (funct3 == 3'b110)
                alu_control = 3'b100;

        end

    end

endmodule

rtl/instruction_memory.sv
module instruction_memory (
    input  logic [31:0] address,
    output logic [31:0] instruction
);

    logic [31:0] memory [0:15];

    initial begin

        // ADD x3, x1, x2
        memory[0] = 32'h002081B3;

        // SUB x4, x3, x1
        memory[1] = 32'h40118233;

        // AND x5, x3, x4
        memory[2] = 32'h0041F2B3;

        // OR x6, x3, x4
        memory[3] = 32'h0041E333;

    end

    always_comb begin

        instruction = memory[address >> 2];

    end

endmodule

rtl/program_counter.sv
module program_counter (
    input  logic        clk,
    input  logic        reset,
    output logic [31:0] pc
);

    always_ff @(posedge clk) begin

        if (reset)
            pc <= 32'b0;

        else
            pc <= pc + 32'd4;

    end

endmodule

rtl/datapath.sv
module datapath (
    input logic clk,
    input logic reset
);

    // -------------------------
    // PC
    // -------------------------

    logic [31:0] pc;

    program_counter pc_unit (
        .clk(clk),
        .reset(reset),
        .pc(pc)
    );


    // -------------------------
    // Instruction Memory
    // -------------------------

    logic [31:0] instruction;

    instruction_memory imem (
        .address(pc),
        .instruction(instruction)
    );


    // -------------------------
    // Decoder
    // -------------------------

    logic [4:0] rs1;
    logic [4:0] rs2;
    logic [4:0] rd;

    logic [2:0] alu_control;

    decoder decoder_unit (
        .instruction(instruction),
        .rs1(rs1),
        .rs2(rs2),
        .rd(rd),
        .alu_control(alu_control)
    );


    // -------------------------
    // Register File
    // -------------------------

    logic [31:0] read_data1;
    logic [31:0] read_data2;

    logic [31:0] write_data;
    logic write_enable;

    register_file reg_file (
        .clk(clk),
        .reset(reset),

        .rs1(rs1),
        .rs2(rs2),

        .rd(rd),
        .write_data(write_data),
        .write_enable(write_enable),

        .read_data1(read_data1),
        .read_data2(read_data2)
    );


    // -------------------------
    // Control Unit
    // -------------------------

    logic reg_write;

    control_unit control_unit_inst (
        .alu_control(alu_control),
        .reg_write(reg_write)
    );


    // -------------------------
    // ALU
    // -------------------------

    logic [31:0] alu_result;

    alu alu_unit (
        .a(read_data1),
        .b(read_data2),
        .alu_control(alu_control),
        .result(alu_result)
    );


    // ALU result goes back to Register File
    assign write_data = alu_result;

    // Control whether register file writes
    assign write_enable = reg_write;

    always @(posedge clk) begin
        $display("PC=%0d Instruction=%h rs1=%0d rs2=%0d rd=%0d ALU_Result=%0d",
                 pc,
                 instruction,
                 rs1,
                 rs2,
                 rd,
                 alu_result);
    end

endmodule

tb/datapath_tb.sv
module datapath_tb;

    logic clk;
    logic reset;

    datapath dut (
        .clk(clk),
        .reset(reset)
    );

    always #5 clk = ~clk;

    initial begin
        $dumpfile("datapath.vcd");
        $dumpvars(0, datapath_tb);

        clk = 0;
        reset = 1;

        #12;
        reset = 0;

        #200;
        $finish;
    end

endmodule

datapath.vcd
$date
	Sun Aug 16 18:58:45 2026
$end
$version
	Icarus Verilog
$end
$timescale
	1s
$end
$scope module datapath_tb $end
$var reg 1 ! clk $end
$var reg 1 " reset $end
$scope module dut $end
$var wire 1 ! clk $end
$var wire 1 " reset $end
$var wire 32 # write_data [31:0] $end
$var wire 1 $ write_enable $end
$var wire 5 % rs2 [4:0] $end
$var wire 5 & rs1 [4:0] $end
$var wire 1 ' reg_write $end
$var wire 32 ( read_data2 [31:0] $end
$var wire 32 ) read_data1 [31:0] $end
$var wire 5 * rd [4:0] $end
$var wire 32 + pc [31:0] $end
$var wire 32 , instruction [31:0] $end
$var wire 32 - alu_result [31:0] $end
$var wire 3 . alu_control [2:0] $end
$scope module alu_unit $end
$var wire 32 / b [31:0] $end
$var wire 3 0 alu_control [2:0] $end
$var wire 32 1 a [31:0] $end
$var reg 32 2 result [31:0] $end
$upscope $end
$scope module control_unit_inst $end
$var wire 3 3 alu_control [2:0] $end
$var reg 1 ' reg_write $end
$upscope $end
$scope module decoder_unit $end
$var wire 5 4 rs2 [4:0] $end
$var wire 5 5 rs1 [4:0] $end
$var wire 5 6 rd [4:0] $end
$var wire 7 7 opcode [6:0] $end
$var wire 32 8 instruction [31:0] $end
$var wire 7 9 funct7 [6:0] $end
$var wire 3 : funct3 [2:0] $end
$var reg 3 ; alu_control [2:0] $end
$upscope $end
$scope module imem $end
$var wire 32 < address [31:0] $end
$var reg 32 = instruction [31:0] $end
$upscope $end
$scope module pc_unit $end
$var wire 1 ! clk $end
$var wire 1 " reset $end
$var reg 32 > pc [31:0] $end
$upscope $end
$scope module reg_file $end
$var wire 1 ! clk $end
$var wire 5 ? rd [4:0] $end
$var wire 1 " reset $end
$var wire 5 @ rs1 [4:0] $end
$var wire 5 A rs2 [4:0] $end
$var wire 32 B write_data [31:0] $end
$var wire 1 $ write_enable $end
$var reg 32 C read_data1 [31:0] $end
$var reg 32 D read_data2 [31:0] $end
$var integer 32 E i [31:0] $end
$upscope $end
$upscope $end
$upscope $end
$enddefinitions $end
$comment Show the parameter values. $end
$dumpall
$end
#0
$dumpvars
bx E
bx D
bx C
b0 B
bx A
bx @
bx ?
bx >
bx =
bx <
b0 ;
bx :
bx 9
bx 8
bx 7
bx 6
bx 5
bx 4
b0 3
b0 2
bx 1
b0 0
bx /
b0 .
b0 -
bx ,
bx +
bx *
bx )
bx (
0'
bx &
bx %
0$
b0 #
1"
0!
$end
#5
b11110 #
b11110 B
b11110 -
b11110 2
1$
1'
b10100 (
b10100 /
b10100 D
b1010 )
b1010 1
b1010 C
b1 .
b1 0
b1 3
b1 ;
b0 9
b10 %
b10 4
b10 A
b1 &
b1 5
b1 @
b0 :
b11 *
b11 6
b11 ?
b110011 7
b1000001000000110110011 ,
b1000001000000110110011 8
b1000001000000110110011 =
b0 +
b0 <
b0 >
b100000 E
1!
#10
0!
#12
0"
#15
1$
1'
b10100 #
b10100 B
b10100 -
b10100 2
b10 .
b10 0
b10 3
b10 ;
b1010 (
b1010 /
b1010 D
b11110 )
b11110 1
b11110 C
b100000 9
b1 %
b1 4
b1 A
b11 &
b11 5
b11 @
b100 *
b100 6
b100 ?
b1000000000100011000001000110011 ,
b1000000000100011000001000110011 8
b1000000000100011000001000110011 =
b100 +
b100 <
b100 >
1!
#20
0!
#25
1$
1'
b10100 (
b10100 /
b10100 D
b11 .
b11 0
b11 3
b11 ;
b0 9
b100 %
b100 4
b100 A
b111 :
b101 *
b101 6
b101 ?
b10000011111001010110011 ,
b10000011111001010110011 8
b10000011111001010110011 =
b1000 +
b1000 <
b1000 >
1!
#30
0!
#35
b11110 #
b11110 B
b11110 -
b11110 2
1$
1'
b100 .
b100 0
b100 3
b100 ;
b110 :
b110 *
b110 6
b110 ?
b10000011110001100110011 ,
b10000011110001100110011 8
b10000011110001100110011 =
b1100 +
b1100 <
b1100 >
1!
#40
0!
#45
b0 #
b0 B
b0 -
b0 2
0$
0'
bx (
bx /
bx D
bx )
bx 1
bx C
b0 .
b0 0
b0 3
b0 ;
bx 9
bx %
bx 4
bx A
bx &
bx 5
bx @
bx :
bx *
bx 6
bx ?
bx 7
bx ,
bx 8
bx =
b10000 +
b10000 <
b10000 >
1!
#50
0!
#55
b10100 +
b10100 <
b10100 >
1!
#60
0!
#65
b11000 +
b11000 <
b11000 >
1!
#70
0!
#75
b11100 +
b11100 <
b11100 >
1!
#80
0!
#85
b100000 +
b100000 <
b100000 >
1!
#90
0!
#95
b100100 +
b100100 <
b100100 >
1!
#100
0!
#105
b101000 +
b101000 <
b101000 >
1!
#110
0!
#115
b101100 +
b101100 <
b101100 >
1!
#120
0!
#125
b110000 +
b110000 <
b110000 >
1!
#130
0!
#135
b110100 +
b110100 <
b110100 >
1!
#140
0!
#145
b111000 +
b111000 <
b111000 >
1!
#150
0!
#155
b111100 +
b111100 <
b111100 >
1!
#160
0!
#165
b1000000 +
b1000000 <
b1000000 >
1!
#170
0!
#175
b1000100 +
b1000100 <
b1000100 >
1!
#180
0!
#185
b1001000 +
b1001000 <
b1001000 >
1!
#190
0!
#195
b1001100 +
b1001100 <
b1001100 >
1!
#200
0!
#205
b1010000 +
b1010000 <
b1010000 >
1!
