rtl/data_memory.sv
module data_memory (
    input  logic        clk,
    input  logic        reset,

    input  logic [31:0] address,
    input  logic [31:0] write_data,

    input  logic        mem_read,
    input  logic        mem_write,

    output logic [31:0] read_data
);

    logic [31:0] memory [0:255];

    integer i;

    // Initialize memory
    always_ff @(posedge clk) begin

        if (reset) begin
            for (i = 0; i < 256; i = i + 1)
                memory[i] <= 32'b0;
        end

        else if (mem_write) begin
            memory[address >> 2] <= write_data;
        end

    end

    // Read memory
    always_comb begin

        if (mem_read)
            read_data = memory[address >> 2];

        else
            read_data = 32'b0;

    end

endmodule

rtl/alu.sv
// ============================================================
// ALU — Arithmetic Logic Unit
// Supported operations (alu_control encoding):
//   3'b000  ADD
//   3'b001  SUB
//   3'b010  AND
//   3'b011  OR
//   3'b100  XOR  (reserved for future use)
// ============================================================

module alu (
    input  logic [31:0] a,
    input  logic [31:0] b,
    input  logic [2:0]  alu_control,
    output logic [31:0] result
);

    always_comb begin
        case (alu_control)
            3'b000:  result = a + b;        // ADD
            3'b001:  result = a - b;        // SUB
            3'b010:  result = a & b;        // AND
            3'b011:  result = a | b;        // OR
            3'b100:  result = a ^ b;        // XOR
            default: result = 32'b0;
        endcase
    end

endmodule

rtl/immediate_generator.sv
// ============================================================
// Immediate Generator — sign-extends the immediate field
// for each RISC-V instruction format.
//
// Uses continuous assign (not always_comb) to avoid Icarus
// "constant selects" warnings while remaining synthesisable.
//
// Formats supported:
//   I-type : ADDI, LW, JALR  — 12-bit sign-extended
//   S-type : SW               — 12-bit sign-extended split field
//   B-type : BEQ, BNE         — 13-bit sign-extended (LSB=0)
//   J-type : JAL              — 21-bit sign-extended (LSB=0)
//   R-type : (no immediate used — falls through to I-type default,
//             but alu_src=0 so result is never consumed)
// ============================================================

module immediate_generator (
    input  logic [31:0] instruction,
    output logic [31:0] immediate
);

    logic [6:0] opcode;
    assign opcode = instruction[6:0];

    // I-type (default): sign-extend bits [31:20]
    logic [31:0] imm_i;
    assign imm_i = {{20{instruction[31]}}, instruction[31:20]};

    // S-type: split immediate [31:25] | [11:7]
    logic [31:0] imm_s;
    assign imm_s = {{20{instruction[31]}}, instruction[31:25], instruction[11:7]};

    // B-type: [31][7][30:25][11:8] << 1
    logic [31:0] imm_b;
    assign imm_b = {{19{instruction[31]}}, instruction[31], instruction[7],
                    instruction[30:25], instruction[11:8], 1'b0};

    // J-type: [31][19:12][20][30:21] << 1
    logic [31:0] imm_j;
    assign imm_j = {{11{instruction[31]}}, instruction[31], instruction[19:12],
                    instruction[20], instruction[30:21], 1'b0};

    // Select based on opcode
    always_comb begin
        case (opcode)
            7'b0100011: immediate = imm_s;  // SW
            7'b1100011: immediate = imm_b;  // BEQ, BNE
            7'b1101111: immediate = imm_j;  // JAL
            default:    immediate = imm_i;  // ADDI, LW, JALR, R-type (unused)
        endcase
    end

endmodule

rtl/register_file.sv
module register_file (
    input  logic        clk,
    input  logic        reset,

    input  logic [4:0]  rs1,
    input  logic [4:0]  rs2,

    input  logic [4:0]  rd,
    input  logic [31:0] write_data,
    input  logic        write_enable,

    output logic [31:0] read_data1,
    output logic [31:0] read_data2
);

    // 32 registers, each 32 bits wide
    logic [31:0] registers [0:31];

    integer i;

    // Write operation
    always_ff @(posedge clk) begin

        if (reset) begin

            for (i = 0; i < 32; i = i + 1)
                registers[i] <= 32'b0;

            registers[1] <= 32'd10;
            registers[2] <= 32'd20;

        end
        else if (write_enable && (rd != 5'b00000)) begin

            registers[rd] <= write_data;

        end

    end

    // Read operations
    always_comb begin

        if (rs1 == 5'b00000)
            read_data1 = 32'b0;
        else
            read_data1 = registers[rs1];

        if (rs2 == 5'b00000)
            read_data2 = 32'b0;
        else
            read_data2 = registers[rs2];

    end

endmodule

rtl/control_unit.sv
module control_unit (
    input  logic [31:0] instruction,

    output logic       reg_write,
    output logic       alu_src,
    output logic       mem_read,
    output logic       mem_write,
    output logic       mem_to_reg,
    output logic       branch,
    output logic       branch_ne,
    output logic       jump,
    output logic       jalr
);

    logic [6:0] opcode;
    logic [2:0] funct3;

    assign opcode = instruction[6:0];
    assign funct3 = instruction[14:12];

    always_comb begin
        reg_write = 1'b0;
        alu_src   = 1'b0;
        mem_read  = 1'b0;
        mem_write = 1'b0;
        mem_to_reg = 1'b0;
        branch    = 1'b0;
        branch_ne = 1'b0;
        jump      = 1'b0;
        jalr      = 1'b0;

        // R-type: ADD, SUB, AND, OR
        if (opcode == 7'b0110011) begin
            reg_write = 1'b1;
        end

        // I-type: ADDI
        else if (opcode == 7'b0010011 && funct3 == 3'b000) begin
            reg_write = 1'b1;
            alu_src   = 1'b1;
        end

        // I-type: LW
        else if (opcode == 7'b0000011 && funct3 == 3'b010) begin
            reg_write  = 1'b1;
            alu_src    = 1'b1;
            mem_read   = 1'b1;
            mem_to_reg = 1'b1;
        end

        // S-type: SW
        else if (opcode == 7'b0100011 && funct3 == 3'b010) begin
            alu_src   = 1'b1;
            mem_write = 1'b1;
        end

        // B-type: BEQ, BNE
        else if (opcode == 7'b1100011) begin
            if (funct3 == 3'b000)
                branch = 1'b1;
            else if (funct3 == 3'b001)
                branch_ne = 1'b1;
        end

        // J-type: JAL
        else if (opcode == 7'b1101111) begin
            reg_write = 1'b1;
            jump      = 1'b1;
        end

        // I-type: JALR
        else if (opcode == 7'b1100111 && funct3 == 3'b000) begin
            reg_write = 1'b1;
            alu_src   = 1'b1;
            jalr      = 1'b1;
        end
    end

endmodule

rtl/decoder.sv
// ============================================================
// Decoder — extracts register indices and generates alu_control
//
// alu_control encoding (must match alu.sv):
//   3'b000  ADD   (R-type ADD, I-type ADDI, LW addr, SW addr, JALR target)
//   3'b001  SUB   (R-type SUB, B-type comparison)
//   3'b010  AND   (R-type AND)
//   3'b011  OR    (R-type OR)
//   3'b100  XOR   (reserved)
// ============================================================

module decoder (
    input  logic [31:0] instruction,

    output logic [4:0]  rs1,
    output logic [4:0]  rs2,
    output logic [4:0]  rd,
    output logic [2:0]  alu_control
);

    logic [6:0] opcode;
    logic [2:0] funct3;
    logic [6:0] funct7;

    assign opcode = instruction[6:0];
    assign rd     = instruction[11:7];
    assign funct3 = instruction[14:12];
    assign rs1    = instruction[19:15];
    assign rs2    = instruction[24:20];
    assign funct7 = instruction[31:25];

    always_comb begin
        alu_control = 3'b000; // default: ADD

        // R-type: ADD, SUB, AND, OR
        if (opcode == 7'b0110011) begin
            if (funct3 == 3'b000) begin
                if (funct7 == 7'b0000000)
                    alu_control = 3'b000; // ADD
                else if (funct7 == 7'b0100000)
                    alu_control = 3'b001; // SUB
            end
            else if (funct3 == 3'b111)
                alu_control = 3'b010;     // AND
            else if (funct3 == 3'b110)
                alu_control = 3'b011;     // OR
        end

        // I-type: ADDI  — ALU computes rs1 + imm
        else if (opcode == 7'b0010011) begin
            if (funct3 == 3'b000)
                alu_control = 3'b000;     // ADD
        end

        // I-type: LW  — ALU computes base + offset address
        else if (opcode == 7'b0000011) begin
            if (funct3 == 3'b010)
                alu_control = 3'b000;     // ADD
        end

        // I-type: JALR  — ALU computes rs1 + imm jump target
        else if (opcode == 7'b1100111) begin
            if (funct3 == 3'b000)
                alu_control = 3'b000;     // ADD
        end

        // S-type: SW  — ALU computes base + offset address
        else if (opcode == 7'b0100011) begin
            if (funct3 == 3'b010)
                alu_control = 3'b000;     // ADD
        end

        // B-type: BEQ, BNE  — ALU performs SUB; zero flag used for branch
        else if (opcode == 7'b1100011) begin
            if (funct3 == 3'b000 || funct3 == 3'b001)
                alu_control = 3'b001;     // SUB
        end

        // J-type: JAL  — no ALU computation needed; target = PC + imm
        // alu_control stays at default 3'b000 (result unused)
    end

endmodule

rtl/instruction_memory.sv
// ============================================================
// Instruction Memory — 32-word ROM (PC-addressed, word-indexed)
//
// Default program exercises all 11 target instructions:
//   ADD, SUB, AND, OR, ADDI, SW, LW, BEQ, BNE, JAL, JALR
//
// Uninitialized slots default to NOP (ADDI x0, x0, 0 = 32'h00000013).
// ============================================================

module instruction_memory (
    input  logic [31:0] address,
    output logic [31:0] instruction
);

    logic [31:0] memory [0:31];

    initial begin
        // --- Fill entire ROM with NOP first ---
        // NOP = ADDI x0, x0, 0 = 32'h00000013
        integer k;
        for (k = 0; k < 32; k = k + 1)
            memory[k] = 32'h00000013;

        // -----------------------------------------------
        // PC=0  (word 0):  ADDI x1, x0, 10   -> x1 = 10
        memory[0]  = 32'h00A00093;

        // PC=4  (word 1):  ADDI x2, x0, 5    -> x2 = 5
        memory[1]  = 32'h00500113;

        // PC=8  (word 2):  ADD  x3, x1, x2   -> x3 = 15
        memory[2]  = 32'h002081B3;

        // PC=12 (word 3):  SUB  x4, x1, x2   -> x4 = 5
        memory[3]  = 32'h40208233;

        // PC=16 (word 4):  AND  x5, x1, x2   -> x5 = 0  (10 & 5 = 0)
        memory[4]  = 32'h0020F2B3;

        // PC=20 (word 5):  OR   x6, x1, x2   -> x6 = 15 (10 | 5 = 15)
        memory[5]  = 32'h0020E333;

        // PC=24 (word 6):  ADDI x7, x0, 100  -> x7 = 100 (memory base)
        memory[6]  = 32'h06400393;

        // PC=28 (word 7):  SW   x3, 0(x7)    -> mem[100] = 15
        memory[7]  = 32'h0033A023;

        // PC=32 (word 8):  LW   x8, 0(x7)    -> x8 = 15
        memory[8]  = 32'h0003A403;

        // PC=36 (word 9):  BEQ  x3, x8, +8   -> x3==x8 (both 15), branch to PC=44
        memory[9]  = 32'h00818463;

        // PC=40 (word 10): ADDI x9, x0, 99   -> SKIPPED by BEQ
        memory[10] = 32'h06300493;

        // PC=44 (word 11): ADDI x10, x0, 1   -> BEQ branch target; x10 = 1
        memory[11] = 32'h00100513;

        // PC=48 (word 12): BNE  x1, x2, +8   -> x1!=x2 (10!=5), branch to PC=56
        memory[12] = 32'h00209463;

        // PC=52 (word 13): ADDI x11, x0, 99  -> SKIPPED by BNE
        memory[13] = 32'h06300593;

        // PC=56 (word 14): ADDI x12, x0, 2   -> BNE branch target; x12 = 2
        memory[14] = 32'h00200613;

        // PC=60 (word 15): JAL  x13, +8      -> x13 = 64, jump to PC=68
        memory[15] = 32'h008006EF;

        // PC=64 (word 16): ADDI x14, x0, 99  -> SKIPPED by JAL
        memory[16] = 32'h06300713;

        // PC=68 (word 17): ADDI x15, x0, 3   -> JAL target; x15 = 3
        memory[17] = 32'h00300793;

        // PC=72 (word 18): ADDI x1, x0, 88   -> x1 = 88 (JALR base)
        memory[18] = 32'h05800093;

        // PC=76 (word 19): JALR x16, 0(x1)   -> x16 = 80, jump to PC=88
        memory[19] = 32'h00008867;

        // PC=80 (word 20): NOP               -> SKIPPED by JALR (pre-filled above)
        // PC=84 (word 21): NOP               -> SKIPPED by JALR (pre-filled above)

        // PC=88 (word 22): ADDI x17, x0, 42  -> JALR landing pad; x17 = 42
        memory[22] = 32'h02A00893;

        // PC=92+ : NOP (pre-filled above)
    end

    always_comb begin
        instruction = memory[address >> 2];
    end

endmodule

rtl/program_counter.sv
module program_counter (
    input  logic        clk,
    input  logic        reset,
    input  logic [31:0] next_pc,
    output logic [31:0] pc
);

    always_ff @(posedge clk) begin

        if (reset)
            pc <= 32'b0;

        else
            pc <= next_pc;

    end

endmodule

rtl/datapath.sv
// ============================================================
// Datapath — Single-cycle RV32I top-level integration
//
// Supported instructions: ADD, SUB, AND, OR, ADDI,
//                         LW, SW, BEQ, BNE, JAL, JALR
//
// SystemVerilog Assertions (SVA):
//   1. x0 must always read as zero
//   2. PC must always be word-aligned (pc[1:0] == 2'b00)
//   3. At most one memory operation active at a time
//   4. reg_write must be de-asserted for branch/store instructions
//   5. write_enable must never target x0
// ============================================================

module datapath (
    input logic clk,
    input logic reset
);

    // -------------------------------------------------------
    // Program Counter
    // -------------------------------------------------------

    logic [31:0] pc;
    logic [31:0] pc_plus_4;
    logic [31:0] next_pc;
    logic        branch_taken;

    assign pc_plus_4 = pc + 32'd4;

    program_counter pc_unit (
        .clk    (clk),
        .reset  (reset),
        .next_pc(next_pc),
        .pc     (pc)
    );

    // -------------------------------------------------------
    // Instruction Memory
    // -------------------------------------------------------

    logic [31:0] instruction;

    instruction_memory imem (
        .address    (pc),
        .instruction(instruction)
    );

    // -------------------------------------------------------
    // Decoder
    // -------------------------------------------------------

    logic [4:0] rs1;
    logic [4:0] rs2;
    logic [4:0] rd;
    logic [2:0] alu_control;

    decoder decoder_unit (
        .instruction(instruction),
        .rs1        (rs1),
        .rs2        (rs2),
        .rd         (rd),
        .alu_control(alu_control)
    );

    // -------------------------------------------------------
    // Control Unit
    // -------------------------------------------------------

    logic reg_write;
    logic alu_src;
    logic mem_read;
    logic mem_write;
    logic mem_to_reg;
    logic branch;
    logic branch_ne;
    logic jump;
    logic jalr;

    control_unit control_unit_inst (
        .instruction(instruction),
        .reg_write  (reg_write),
        .alu_src    (alu_src),
        .mem_read   (mem_read),
        .mem_write  (mem_write),
        .mem_to_reg (mem_to_reg),
        .branch     (branch),
        .branch_ne  (branch_ne),
        .jump       (jump),
        .jalr       (jalr)
    );

    // -------------------------------------------------------
    // Register File
    // -------------------------------------------------------

    logic [31:0] read_data1;
    logic [31:0] read_data2;
    logic [31:0] write_data;
    logic        write_enable;

    register_file reg_file (
        .clk         (clk),
        .reset       (reset),
        .rs1         (rs1),
        .rs2         (rs2),
        .rd          (rd),
        .write_data  (write_data),
        .write_enable(write_enable),
        .read_data1  (read_data1),
        .read_data2  (read_data2)
    );

    // -------------------------------------------------------
    // Immediate Generator
    // -------------------------------------------------------

    logic [31:0] immediate;

    immediate_generator imm_gen (
        .instruction(instruction),
        .immediate  (immediate)
    );

    // -------------------------------------------------------
    // ALU input mux: register value or sign-extended immediate
    // -------------------------------------------------------

    logic [31:0] alu_input_b;
    assign alu_input_b = alu_src ? immediate : read_data2;

    // -------------------------------------------------------
    // ALU
    // -------------------------------------------------------

    logic [31:0] alu_result;
    logic        zero;

    alu alu_unit (
        .a          (read_data1),
        .b          (alu_input_b),
        .alu_control(alu_control),
        .result     (alu_result)
    );

    // zero flag: high when ALU result is 0 (used by BEQ/BNE)
    assign zero = (alu_result == 32'b0);

    // -------------------------------------------------------
    // Branch / Jump target and PC selection
    // -------------------------------------------------------

    logic [31:0] branch_target;
    assign branch_target = pc + immediate;

    assign branch_taken = (branch && zero) || (branch_ne && !zero);

    // PC mux priority: JALR > branch/JAL > PC+4
    assign next_pc = jalr         ? (alu_result & ~32'h1)  // JALR: rs1+imm, clear LSB
                   : (branch_taken || jump) ? branch_target
                   : pc_plus_4;

    // -------------------------------------------------------
    // Data Memory
    // -------------------------------------------------------

    logic [31:0] memory_read_data;

    data_memory data_mem (
        .clk       (clk),
        .reset     (reset),
        .address   (alu_result),
        .write_data(read_data2),
        .mem_read  (mem_read),
        .mem_write (mem_write),
        .read_data (memory_read_data)
    );

    // -------------------------------------------------------
    // Writeback mux
    //   JAL/JALR  → save return address (PC+4)
    //   LW        → memory read data
    //   default   → ALU result
    // -------------------------------------------------------
    assign write_data   = (jump || jalr) ? pc_plus_4
                        : mem_to_reg     ? memory_read_data
                        :                  alu_result;

    assign write_enable = reg_write;

    // ===========================================================
    // SystemVerilog Assertions (simulation only)
    // ===========================================================
`ifndef SYNTHESIS

    // SVA 1: x0 must always be zero (hardwired)
    // (Also checked inside register_file.sv; duplicated here at
    //  the integration level so it appears in datapath waveforms.)
    always @(posedge clk) begin
        if (!reset)
            assert (reg_file.registers[0] == 32'b0)
                else $error("[SVA1] x0 must always be zero — got %0h at pc=%0h",
                            reg_file.registers[0], pc);
    end

    // SVA 2: PC must always be word-aligned (RISC-V ISA §2.2)
    always @(posedge clk) begin
        if (!reset)
            assert (pc[1:0] == 2'b00)
                else $error("[SVA2] PC alignment violation — pc=%0h", pc);
    end

    // SVA 3: mem_read and mem_write cannot both be asserted simultaneously
    always @(posedge clk) begin
        if (!reset)
            assert (!(mem_read && mem_write))
                else $error("[SVA3] mem_read and mem_write both high at pc=%0h", pc);
    end

    // SVA 4: reg_write must be 0 for branch and store instructions
    always @(posedge clk) begin
        if (!reset) begin
            if (branch || branch_ne)
                assert (reg_write == 1'b0)
                    else $error("[SVA4] reg_write asserted during branch at pc=%0h", pc);
            if (mem_write)
                assert (reg_write == 1'b0)
                    else $error("[SVA4] reg_write asserted during store at pc=%0h", pc);
        end
    end

    // SVA 5: the register file's write guard must hold —
    // if write_enable is high AND rd happens to be x0, the register file
    // will silently discard the write (by design).  What we actually want
    // to assert is that x0 never gets a non-zero value committed — which
    // is already covered by SVA1.  Here we assert the structural property:
    // no instruction that SHOULD write a meaningful result targets x0 via
    // an unintentional path (i.e., reg_write from control unit is only set
    // for instructions that have a valid rd field).
    // We verify this as: after reset, registers[0] stays 0 every cycle.
    // (SVA1 already covers this; SVA5 adds the pre-condition check.)
    always @(posedge clk) begin
        if (!reset && write_enable && rd == 5'b00000)
            assert (reg_file.registers[0] == 32'b0)
                else $error("[SVA5] x0 was modified — registers[0]=%0h at pc=%0h",
                            reg_file.registers[0], pc);
    end
`endif

endmodule

tb/datapath_tb.sv
module datapath_tb;

    logic clk;
    logic reset;

    datapath dut (
        .clk(clk),
        .reset(reset)
    );

    always #5 clk = ~clk;

    task check_reg(input int addr, input int expected, input string name);
        if (dut.reg_file.registers[addr] !== expected) begin
            $display("FAIL %s: x%0d=%0d (expected %0d)", name, addr, dut.reg_file.registers[addr], expected);
            $fatal(1);
        end
        else
            $display("PASS %s: x%0d=%0d", name, addr, expected);
    endtask

    initial begin
        $dumpfile("datapath.vcd");
        $dumpvars(0, datapath_tb);

        clk = 0;
        reset = 1;

        #12;
        reset = 0;

        // Enough cycles to run through the full program including JALR
        #400;

        $display("\n=== Register File Verification ===");
        check_reg(1,  88,  "x1 after JALR setup");
        check_reg(2,  5,   "x2");
        check_reg(3,  15,  "x3 ADD result");
        check_reg(4,  5,   "x4 SUB result");
        check_reg(5,  0,   "x5 AND result");
        check_reg(6,  15,  "x6 OR result");
        check_reg(7,  100, "x7 memory base");
        check_reg(8,  15,  "x8 LW result");
        check_reg(9,  0,   "x9 skipped by BEQ");
        check_reg(10, 1,   "x10 BEQ target");
        check_reg(11, 0,   "x11 skipped by BNE");
        check_reg(12, 2,   "x12 BNE target");
        check_reg(13, 64,  "x13 JAL link");
        check_reg(14, 0,   "x14 skipped by JAL");
        check_reg(15, 3,   "x15 JAL target");
        check_reg(16, 80,  "x16 JALR link");
        check_reg(17, 42,  "x17 JALR landing");

        if (dut.data_mem.memory[25] !== 32'd15)
            $fatal(1, "FAIL mem[100]: got %0d expected 15", dut.data_mem.memory[25]);
        else
            $display("PASS mem[100]=15 (SW/LW)");

        $display("\nAll datapath tests passed.");
        $finish;
    end

endmodule

datapath.vcd
$date
	Mon Aug 17 03:22:42 2026
$end
$version
	Icarus Verilog
$end
$timescale
	1s
$end
$scope module datapath_tb $end
$var reg 1 ! clk $end
$var reg 1 " reset $end
$scope module dut $end
$var wire 1 # branch_taken $end
$var wire 1 ! clk $end
$var wire 1 " reset $end
$var wire 1 $ write_enable $end
$var wire 1 % zero $end
$var wire 32 & write_data [31:0] $end
$var wire 5 ' rs2 [4:0] $end
$var wire 5 ( rs1 [4:0] $end
$var wire 1 ) reg_write $end
$var wire 32 * read_data2 [31:0] $end
$var wire 32 + read_data1 [31:0] $end
$var wire 5 , rd [4:0] $end
$var wire 32 - pc_plus_4 [31:0] $end
$var wire 32 . pc [31:0] $end
$var wire 32 / next_pc [31:0] $end
$var wire 32 0 memory_read_data [31:0] $end
$var wire 1 1 mem_write $end
$var wire 1 2 mem_to_reg $end
$var wire 1 3 mem_read $end
$var wire 1 4 jump $end
$var wire 1 5 jalr $end
$var wire 32 6 instruction [31:0] $end
$var wire 32 7 immediate [31:0] $end
$var wire 32 8 branch_target [31:0] $end
$var wire 1 9 branch_ne $end
$var wire 1 : branch $end
$var wire 1 ; alu_src $end
$var wire 32 < alu_result [31:0] $end
$var wire 32 = alu_input_b [31:0] $end
$var wire 3 > alu_control [2:0] $end
$scope module alu_unit $end
$var wire 32 ? b [31:0] $end
$var wire 3 @ alu_control [2:0] $end
$var wire 32 A a [31:0] $end
$var reg 32 B result [31:0] $end
$upscope $end
$scope module control_unit_inst $end
$var wire 7 C opcode [6:0] $end
$var wire 32 D instruction [31:0] $end
$var wire 3 E funct3 [2:0] $end
$var reg 1 ; alu_src $end
$var reg 1 : branch $end
$var reg 1 9 branch_ne $end
$var reg 1 5 jalr $end
$var reg 1 4 jump $end
$var reg 1 3 mem_read $end
$var reg 1 2 mem_to_reg $end
$var reg 1 1 mem_write $end
$var reg 1 ) reg_write $end
$upscope $end
$scope module data_mem $end
$var wire 32 F address [31:0] $end
$var wire 1 ! clk $end
$var wire 1 3 mem_read $end
$var wire 1 1 mem_write $end
$var wire 1 " reset $end
$var wire 32 G write_data [31:0] $end
$var reg 32 H read_data [31:0] $end
$var integer 32 I i [31:0] $end
$upscope $end
$scope module decoder_unit $end
$var wire 5 J rs2 [4:0] $end
$var wire 5 K rs1 [4:0] $end
$var wire 5 L rd [4:0] $end
$var wire 7 M opcode [6:0] $end
$var wire 32 N instruction [31:0] $end
$var wire 7 O funct7 [6:0] $end
$var wire 3 P funct3 [2:0] $end
$var reg 3 Q alu_control [2:0] $end
$upscope $end
$scope module imem $end
$var wire 32 R address [31:0] $end
$var reg 32 S instruction [31:0] $end
$scope begin $unm_blk_31 $end
$var integer 32 T k [31:0] $end
$upscope $end
$upscope $end
$scope module imm_gen $end
$var wire 32 U instruction [31:0] $end
$var wire 7 V opcode [6:0] $end
$var wire 32 W imm_s [31:0] $end
$var wire 32 X imm_j [31:0] $end
$var wire 32 Y imm_i [31:0] $end
$var wire 32 Z imm_b [31:0] $end
$var reg 32 [ immediate [31:0] $end
$upscope $end
$scope module pc_unit $end
$var wire 1 ! clk $end
$var wire 32 \ next_pc [31:0] $end
$var wire 1 " reset $end
$var reg 32 ] pc [31:0] $end
$upscope $end
$scope module reg_file $end
$var wire 1 ! clk $end
$var wire 5 ^ rd [4:0] $end
$var wire 1 " reset $end
$var wire 5 _ rs1 [4:0] $end
$var wire 5 ` rs2 [4:0] $end
$var wire 32 a write_data [31:0] $end
$var wire 1 $ write_enable $end
$var reg 32 b read_data1 [31:0] $end
$var reg 32 c read_data2 [31:0] $end
$var integer 32 d i [31:0] $end
$upscope $end
$upscope $end
$scope task check_reg $end
$var integer 32 e addr [31:0] $end
$var integer 32 f expected [31:0] $end
$upscope $end
$upscope $end
$enddefinitions $end
$comment Show the parameter values. $end
$dumpall
$end
#0
$dumpvars
b0 f
b0 e
bx d
bx c
bx b
bx a
bx `
bx _
bx ^
bx ]
bx \
bx [
bx0 Z
bx Y
bx0 X
bx W
bx V
bx U
b100000 T
bx S
bx R
b0 Q
bx P
bx O
bx N
bx M
bx L
bx K
bx J
bx I
b0 H
bx G
bx F
bx E
bx D
bx C
bx B
bx A
b0 @
bx ?
b0 >
bx =
bx <
0;
0:
09
bx 8
bx 7
bx 6
05
04
03
02
01
b0 0
bx /
bx .
bx -
bx ,
bx +
bx *
0)
bx (
bx '
bx &
x%
0$
0#
1"
0!
$end
#5
b1010 &
b1010 a
b100000000000 Z
b1010 X
0%
b1010 <
b1010 B
b1010 F
b1010 =
b1010 ?
b1010 8
b1010 7
b1010 [
b1010 Y
b1 W
b0 *
b0 G
b0 c
b0 +
b0 A
b0 b
1;
1$
1)
b100 /
b100 \
b10011 V
b0 O
b1010 '
b1010 J
b1010 `
b0 (
b0 K
b0 _
b0 P
b1 ,
b1 L
b1 ^
b10011 M
b0 E
b10011 C
b101000000000000010010011 6
b101000000000000010010011 D
b101000000000000010010011 N
b101000000000000010010011 S
b101000000000000010010011 U
b100 -
b0 .
b0 R
b0 ]
b100000 d
b100000000 I
1!
#10
0!
#12
0"
#15
b101 &
b101 a
b101 <
b101 B
b101 F
b101 =
b101 ?
b101 7
b101 [
b10 Z
b100000000100 X
b101 Y
b10 W
b1000 /
b1000 \
b101 '
b101 J
b101 `
b10 ,
b10 L
b10 ^
b10100000000000100010011 6
b10100000000000100010011 D
b10100000000000100010011 N
b10100000000000100010011 S
b10100000000000100010011 U
b1001 8
b1000 -
b100 .
b100 R
b100 ]
1!
#20
0!
#25
b1111 &
b1111 a
b100000000010 Z
b1000000000000010 X
b1111 <
b1111 B
b1111 F
b10 7
b10 [
b10 Y
b11 W
b101 *
b101 G
b101 c
b1010 +
b1010 A
b1010 b
0;
1$
1)
b1100 /
b1100 \
b110011 V
b10 '
b10 J
b10 `
b1 (
b1 K
b1 _
b11 ,
b11 L
b11 ^
b110011 M
b110011 C
b1000001000000110110011 6
b1000001000000110110011 D
b1000001000000110110011 N
b1000001000000110110011 S
b1000001000000110110011 U
b1010 8
b1100 -
b1000 .
b1000 R
b1000 ]
1!
#30
0!
#35
b101 &
b101 a
b10000000010 7
b10000000010 [
b10000000100 Z
b1000010000000010 X
b101 <
b101 B
b101 F
b10000000010 Y
b10000000100 W
b1 >
b1 @
b1 Q
b10000 /
b10000 \
b100000 O
b100 ,
b100 L
b100 ^
b1000000001000001000001000110011 6
b1000000001000001000001000110011 D
b1000000001000001000001000110011 N
b1000000001000001000001000110011 S
b1000000001000001000001000110011 U
b10000001110 8
b10000 -
b1100 .
b1100 R
b1100 ]
1!
#40
0!
#45
b0 &
b0 a
b10 7
b10 [
b100000000100 Z
b1111000000000010 X
1%
b0 <
b0 B
b0 F
b10 Y
b101 W
b10 >
b10 @
b10 Q
1$
1)
b10100 /
b10100 \
b0 O
b111 P
b101 ,
b101 L
b101 ^
b111 E
b1000001111001010110011 6
b1000001111001010110011 D
b1000001111001010110011 N
b1000001111001010110011 S
b1000001111001010110011 U
b10010 8
b10100 -
b10000 .
b10000 R
b10000 ]
1!
#50
0!
#55
b1111 &
b1111 a
b110 Z
b1110000000000010 X
0%
b1111 <
b1111 B
b1111 F
b110 W
b11 >
b11 @
b11 Q
1$
1)
b11000 /
b11000 \
b110 P
b110 ,
b110 L
b110 ^
b110 E
b1000001110001100110011 6
b1000001110001100110011 D
b1000001110001100110011 N
b1000001110001100110011 S
b1000001110001100110011 U
b10110 8
b11000 -
b10100 .
b10100 R
b10100 ]
1!
#60
0!
#65
b1100100 &
b1100100 a
b100001100110 Z
b1100100 X
b1100100 <
b1100100 B
b1100100 F
b1100100 =
b1100100 ?
b1100100 7
b1100100 [
b1100100 Y
b1100111 W
b0 +
b0 A
b0 b
b0 >
b0 @
b0 Q
1;
1$
1)
b11100 /
b11100 \
b10011 V
b11 O
b100 '
b100 J
b100 `
b0 (
b0 K
b0 _
b0 P
b111 ,
b111 L
b111 ^
b10011 M
b0 E
b10011 C
b110010000000000001110010011 6
b110010000000000001110010011 D
b110010000000000001110010011 N
b110010000000000001110010011 S
b110010000000000001110010011 U
b1111100 8
b11100 -
b11000 .
b11000 R
b11000 ]
1!
#70
0!
#75
b0 Z
b111010100000000010 X
b0 =
b0 ?
b0 7
b0 [
b11 Y
b0 W
b1111 *
b1111 G
b1111 c
b1100100 +
b1100100 A
b1100100 b
11
1;
0$
0)
b100000 /
b100000 \
b100011 V
b0 O
b11 '
b11 J
b11 `
b111 (
b111 K
b111 _
b10 P
b0 ,
b0 L
b0 ^
b100011 M
b10 E
b100011 C
b1100111010000000100011 6
b1100111010000000100011 D
b1100111010000000100011 N
b1100111010000000100011 S
b1100111010000000100011 U
b11100 8
b100000 -
b11100 .
b11100 R
b11100 ]
1!
#80
0!
#85
b1111 &
b1111 a
b1000 Z
b111010000000000000 X
b1111 0
b1111 H
b0 Y
b1000 W
b0 *
b0 G
b0 c
12
13
1$
1)
01
1;
b100100 /
b100100 \
b11 V
b0 '
b0 J
b0 `
b1000 ,
b1000 L
b1000 ^
b11 M
b11 C
b111010010000000011 6
b111010010000000011 D
b111010010000000011 N
b111010010000000011 S
b111010010000000011 U
b100000 8
b100100 -
b100000 .
b100000 R
b100000 ]
1!
#90
0!
#95
1#
b0 &
b0 a
b11000000000001000 X
1%
b0 <
b0 B
b0 F
b0 0
b0 H
b1111 =
b1111 ?
b1000 7
b1000 [
b1000 Y
b1111 *
b1111 G
b1111 c
b1111 +
b1111 A
b1111 b
b1 >
b1 @
b1 Q
1:
02
03
0;
0$
0)
b101100 /
b101100 \
b1100011 V
b1000 '
b1000 J
b1000 `
b11 (
b11 K
b11 _
b0 P
b1100011 M
b0 E
b1100011 C
b100000011000010001100011 6
b100000011000010001100011 D
b100000011000010001100011 N
b100000011000010001100011 S
b100000011000010001100011 U
b101100 8
b101000 -
b100100 .
b100100 R
b100100 ]
1!
#100
0!
#105
b1 &
b1 a
0#
b1010 Z
b100000000000 X
0%
b1 <
b1 B
b1 F
b1 =
b1 ?
b1 7
b1 [
b1 Y
b1010 W
b1010 *
b1010 G
b1010 c
b0 +
b0 A
b0 b
b0 >
b0 @
b0 Q
1;
1$
1)
0:
b110000 /
b110000 \
b10011 V
b1 '
b1 J
b1 `
b0 (
b0 K
b0 _
b1010 ,
b1010 L
b1010 ^
b10011 M
b10011 C
b100000000010100010011 6
b100000000010100010011 D
b100000000010100010011 N
b100000000010100010011 S
b100000000010100010011 U
b101101 8
b110000 -
b101100 .
b101100 R
b101100 ]
1!
#110
0!
