rtl/data_memory.sv
module data_memory (
    input  logic        clk,
    input  logic        reset,

    input  logic [31:0] address,
    input  logic [31:0] write_data,

    input  logic        mem_read,
    input  logic        mem_write,

    output logic [31:0] read_data
);

    logic [31:0] memory [0:255];

    integer i;

    // Initialize memory
    always_ff @(posedge clk) begin

        if (reset) begin
            for (i = 0; i < 256; i = i + 1)
                memory[i] <= 32'b0;
        end

        else if (mem_write) begin
            memory[address >> 2] <= write_data;
        end

    end

    // Read memory
    always_comb begin

        if (mem_read)
            read_data = memory[address >> 2];

        else
            read_data = 32'b0;

    end

endmodule

rtl/control_unit.sv
module control_unit (
    input  logic [6:0] opcode,
    input  logic [2:0] alu_control,
    input  logic [2:0] funct3,

    output logic       reg_write,
    output logic       alu_src,
    output logic       branch,
    output logic       branch_ne,
    output logic       jump,
    output logic       jalr
);

    always_comb begin

        reg_write = 1'b0;
        alu_src   = 1'b0;
        branch    = 1'b0;
        branch_ne = 1'b0;
        jump      = 1'b0;
        jalr      = 1'b0;

        // R-type instructions: use register operand B
        if (opcode == 7'b0110011) begin
            reg_write = 1'b1;
            alu_src   = 1'b0;
        end

        // I-type ADDI: use immediate as operand B
        else if (opcode == 7'b0010011) begin
            reg_write = 1'b1;
            alu_src   = 1'b1;
        end

        // I-type LW: use immediate address and memory data for writeback
        else if (opcode == 7'b0000011) begin
            reg_write = 1'b1;
            alu_src   = 1'b1;
        end

        // B-type BEQ/BNE: branch instruction
        else if (opcode == 7'b1100011) begin
            if (funct3 == 3'b000)
                branch = 1'b1;      // BEQ
            else if (funct3 == 3'b001)
                branch_ne = 1'b1;   // BNE
        end

        // J-type JAL: jump and link
        else if (opcode == 7'b1101111) begin
            reg_write = 1'b1;
            jump      = 1'b1;
        end

        // I-type JALR: jump and link register
        else if (opcode == 7'b1100111 && funct3 == 3'b000) begin
            reg_write = 1'b1;
            alu_src   = 1'b1;   // Use immediate (rs1 + immediate)
            jalr      = 1'b1;
        end

    end

endmodule

rtl/alu.sv
// ============================================================
// ALU — Arithmetic Logic Unit
// Supported operations (alu_control encoding):
//   3'b000  ADD
//   3'b001  SUB
//   3'b010  AND
//   3'b011  OR
//   3'b100  XOR  (reserved for future use)
// ============================================================

module alu (
    input  logic [31:0] a,
    input  logic [31:0] b,
    input  logic [2:0]  alu_control,
    output logic [31:0] result
);

    always_comb begin
        case (alu_control)
            3'b000:  result = a + b;        // ADD
            3'b001:  result = a - b;        // SUB
            3'b010:  result = a & b;        // AND
            3'b011:  result = a | b;        // OR
            3'b100:  result = a ^ b;        // XOR
            default: result = 32'b0;
        endcase
    end

endmodule

rtl/immediate_generator.sv
module immediate_generator (
    input  logic [31:0] instruction,
    output logic [31:0] immediate
);

    logic [6:0] opcode;
    assign opcode = instruction[6:0];

    always_comb begin
        // Default: I-type immediate
        immediate = {{20{instruction[31]}}, instruction[31:20]};

        // B-type immediate for BEQ, BNE, etc.
        if (opcode == 7'b1100011) begin
            immediate = {
                {19{instruction[31]}},
                instruction[31],
                instruction[7],
                instruction[30:25],
                instruction[11:8],
                1'b0
            };
        end

        // J-type immediate for JAL
        else if (opcode == 7'b1101111) begin
            immediate = {
                {11{instruction[31]}},
                instruction[31],
                instruction[19:12],
                instruction[20],
                instruction[30:21],
                1'b0
            };
        end
    end

endmodule

rtl/register_file.sv
module register_file (
    input  logic        clk,
    input  logic        reset,

    input  logic [4:0]  rs1,
    input  logic [4:0]  rs2,

    input  logic [4:0]  rd,
    input  logic [31:0] write_data,
    input  logic        write_enable,

    output logic [31:0] read_data1,
    output logic [31:0] read_data2
);

    // 32 registers, each 32 bits wide
    logic [31:0] registers [0:31];

    integer i;

    // Write operation
    always_ff @(posedge clk) begin

        if (reset) begin

            for (i = 0; i < 32; i = i + 1)
                registers[i] <= 32'b0;

            registers[1] <= 32'd10;
            registers[2] <= 32'd20;

        end
        else if (write_enable && (rd != 5'b00000)) begin

            registers[rd] <= write_data;

        end

    end

    // Read operations
    always_comb begin

        if (rs1 == 5'b00000)
            read_data1 = 32'b0;
        else
            read_data1 = registers[rs1];

        if (rs2 == 5'b00000)
            read_data2 = 32'b0;
        else
            read_data2 = registers[rs2];

    end

endmodule

rtl/decoder.sv
module decoder (
    input  logic [31:0] instruction,

    output logic [4:0]  rs1,
    output logic [4:0]  rs2,
    output logic [4:0]  rd,

    output logic [2:0]  alu_control,
    output logic        mem_read,
    output logic        mem_write,
    output logic        mem_to_reg
);

    logic [6:0] opcode;
    logic [2:0] funct3;
    logic [6:0] funct7;

    // Extract fields from the instruction
    assign opcode = instruction[6:0];
    assign rd     = instruction[11:7];
    assign funct3 = instruction[14:12];
    assign rs1    = instruction[19:15];
    assign rs2    = instruction[24:20];
    assign funct7 = instruction[31:25];

    // Decode the instruction
    always_comb begin

        // Defaults
        alu_control = 3'b000;
        mem_read    = 1'b0;
        mem_write   = 1'b0;
        mem_to_reg  = 1'b0;

        // R-type instruction
        if (opcode == 7'b0110011) begin

            // ADD / SUB
            if (funct3 == 3'b000) begin

                if (funct7 == 7'b0000000)
                    alu_control = 3'b001; // ADD

                else if (funct7 == 7'b0100000)
                    alu_control = 3'b010; // SUB

            end

            // AND
            else if (funct3 == 3'b111)
                alu_control = 3'b011;

            // OR
            else if (funct3 == 3'b110)
                alu_control = 3'b100;

        end

        // I-type instruction: ADDI
        else if (opcode == 7'b0010011) begin

            if (funct3 == 3'b000)
                alu_control = 3'b001; // ADDI behaves like ADD

        end

        // I-type instruction: LW
        else if (opcode == 7'b0000011) begin

            if (funct3 == 3'b010) begin
                mem_read   = 1'b1;
                mem_to_reg = 1'b1;
            end

        end

        // S-type instruction: SW
        else if (opcode == 7'b0100011) begin

            if (funct3 == 3'b010)
                mem_write = 1'b1;

        end

        // B-type instruction: BEQ/BNE
        else if (opcode == 7'b1100011) begin

            if (funct3 == 3'b000 || funct3 == 3'b001)
                alu_control = 3'b010; // SUB to compute zero flag for both BEQ and BNE

        end

        // I-type instruction: JALR
        else if (opcode == 7'b1100111) begin
            if (funct3 == 3'b000)
                alu_control = 3'b001; // ADD for rs1 + immediate
        end

    end

endmodule

rtl/instruction_memory.sv
module instruction_memory (
    input  logic [31:0] address,
    output logic [31:0] instruction
);

    logic [31:0] memory [0:31];

    initial begin

        // ADDI x1, x0, 16  (PC=0: x1 = 16)
        memory[0] = 32'h01000093;

        // JALR x5, 4(x1)  (PC=4: jump to x1+4=20, save PC+4=8 to x5)
        memory[1] = 32'h004082E7;

        // skipped (PC=8)
        memory[2] = 32'h00000000;

        // skipped (PC=12)
        memory[3] = 32'h00000000;

        // skipped (PC=16)
        memory[4] = 32'h00000000;

        // skipped (PC=20, will be at address 20>>2 = 5)
        memory[5] = 32'h00000000;

        // ADDI x2, x0, 55  (PC=24: x2 = 55, verification)
        memory[6] = 32'h03700113;

    end

    always_comb begin

        instruction = memory[address >> 2];

    end

endmodule

rtl/program_counter.sv
module program_counter (
    input  logic        clk,
    input  logic        reset,
    input  logic [31:0] next_pc,
    output logic [31:0] pc
);

    always_ff @(posedge clk) begin

        if (reset)
            pc <= 32'b0;

        else
            pc <= next_pc;

    end

endmodule

rtl/datapath.sv
module datapath (
    input logic clk,
    input logic reset
);

    // -------------------------
    // PC
    // -------------------------

    logic [31:0] pc;
    logic [31:0] pc_plus_4;
    logic [31:0] next_pc;
    logic        branch_taken;

    assign pc_plus_4 = pc + 32'd4;

    program_counter pc_unit (
        .clk(clk),
        .reset(reset),
        .next_pc(next_pc),
        .pc(pc)
    );


    // -------------------------
    // Instruction Memory
    // -------------------------

    logic [31:0] instruction;

    instruction_memory imem (
        .address(pc),
        .instruction(instruction)
    );


    // -------------------------
    // Decoder
    // -------------------------

    logic [4:0] rs1;
    logic [4:0] rs2;
    logic [4:0] rd;

    logic [2:0] alu_control;
    logic       mem_read;
    logic       mem_write;
    logic       mem_to_reg;

    decoder decoder_unit (
        .instruction(instruction),
        .rs1(rs1),
        .rs2(rs2),
        .rd(rd),
        .alu_control(alu_control),
        .mem_read(mem_read),
        .mem_write(mem_write),
        .mem_to_reg(mem_to_reg)
    );


    // -------------------------
    // Register File
    // -------------------------

    logic [31:0] read_data1;
    logic [31:0] read_data2;

    logic [31:0] write_data;
    logic write_enable;

    register_file reg_file (
        .clk(clk),
        .reset(reset),

        .rs1(rs1),
        .rs2(rs2),

        .rd(rd),
        .write_data(write_data),
        .write_enable(write_enable),

        .read_data1(read_data1),
        .read_data2(read_data2)
    );


    // -------------------------
    // Immediate Generator
    // -------------------------

    logic [31:0] immediate;
    logic [31:0] alu_input_b;
    logic        alu_src;

    immediate_generator imm_gen (
        .instruction(instruction),
        .immediate(immediate)
    );

    assign alu_input_b = alu_src ? immediate : read_data2;

    // -------------------------
    // ALU
    // -------------------------

    logic [31:0] alu_result;

    alu alu_unit (
        .a(read_data1),
        .b(alu_input_b),
        .alu_control(alu_control),
        .result(alu_result)
    );

    // zero flag: 1 if alu_result == 0, 0 otherwise
    logic        zero;
    assign zero = (alu_result == 32'b0);

    // Declare branch control and jump signals early
    logic        branch;
    logic        branch_ne;
    logic        jump;
    logic        jalr;

    // Branch target: PC + immediate
    logic [31:0] branch_target;
    assign branch_target = pc + immediate;

    // PC MUX: choose between PC+4, branch target, or JALR target
    // JALR: jump to rs1 + immediate
    // BEQ/BNE: branch if condition true to PC + immediate
    // JAL: jump to PC + immediate
    // Default: PC + 4
    assign branch_taken = (branch && zero) || (branch_ne && !zero);
    assign next_pc = jalr ? alu_result : ((branch_taken || jump) ? branch_target : pc_plus_4);



    // -------------------------
    // Control Unit
    // -------------------------

    logic [6:0] opcode;
    logic reg_write;

    assign opcode = instruction[6:0];

    logic [2:0] funct3;
    assign funct3 = instruction[14:12];

    control_unit control_unit_inst (
        .opcode(opcode),
        .alu_control(alu_control),
        .funct3(funct3),
        .reg_write(reg_write),
        .alu_src(alu_src),
        .branch(branch),
        .branch_ne(branch_ne),
        .jump(jump),
        .jalr(jalr)
    );


    // -------------------------
    // Data Memory
    // -------------------------

    logic [31:0] memory_read_data;

    data_memory data_mem (
        .clk(clk),
        .reset(reset),

        .address(alu_result),
        .write_data(read_data2),

        .mem_read(mem_read),
        .mem_write(mem_write),

        .read_data(memory_read_data)
    );


    // Writeback MUX: select between PC+4 (JAL/JALR), memory data (LW), or ALU result
    // Priority: (JAL or JALR) > LW > ALU
    assign write_data = (jump || jalr) ? pc_plus_4 : (mem_to_reg ? memory_read_data : alu_result);

    // Control whether register file writes
    assign write_enable = reg_write;

    always @(posedge clk) begin
        $display("PC=%0d Instruction=%h rs1=%0d rs2=%0d rd=%0d ALU_Result=%0d",
                 pc,
                 instruction,
                 rs1,
                 rs2,
                 rd,
                 alu_result);
    end

endmodule

tb/datapath_tb.sv
module datapath_tb;

    logic clk;
    logic reset;

    datapath dut (
        .clk(clk),
        .reset(reset)
    );

    always #5 clk = ~clk;

    initial begin
        $dumpfile("datapath.vcd");
        $dumpvars(0, datapath_tb);

        clk = 0;
        reset = 1;

        #12;
        reset = 0;

        #200;
        
        // Print register file contents to verify JAL saved PC+4
        $display("\n=== Register File Contents ===");
        $display("x1=%0d", dut.reg_file.registers[1]);
        $display("x5=%0d (should be 8, the return address)", dut.reg_file.registers[5]);
        
        $finish;
    end

endmodule

datapath.vcd
$date
	Mon Aug 17 00:08:22 2026
$end
$version
	Icarus Verilog
$end
$timescale
	1s
$end
$scope module datapath_tb $end
$var reg 1 ! clk $end
$var reg 1 " reset $end
$scope module dut $end
$var wire 1 # branch_taken $end
$var wire 1 ! clk $end
$var wire 1 " reset $end
$var wire 1 $ write_enable $end
$var wire 1 % zero $end
$var wire 32 & write_data [31:0] $end
$var wire 5 ' rs2 [4:0] $end
$var wire 5 ( rs1 [4:0] $end
$var wire 1 ) reg_write $end
$var wire 32 * read_data2 [31:0] $end
$var wire 32 + read_data1 [31:0] $end
$var wire 5 , rd [4:0] $end
$var wire 32 - pc_plus_4 [31:0] $end
$var wire 32 . pc [31:0] $end
$var wire 7 / opcode [6:0] $end
$var wire 32 0 next_pc [31:0] $end
$var wire 32 1 memory_read_data [31:0] $end
$var wire 1 2 mem_write $end
$var wire 1 3 mem_to_reg $end
$var wire 1 4 mem_read $end
$var wire 1 5 jump $end
$var wire 1 6 jalr $end
$var wire 32 7 instruction [31:0] $end
$var wire 32 8 immediate [31:0] $end
$var wire 3 9 funct3 [2:0] $end
$var wire 32 : branch_target [31:0] $end
$var wire 1 ; branch_ne $end
$var wire 1 < branch $end
$var wire 1 = alu_src $end
$var wire 32 > alu_result [31:0] $end
$var wire 32 ? alu_input_b [31:0] $end
$var wire 3 @ alu_control [2:0] $end
$scope module alu_unit $end
$var wire 32 A b [31:0] $end
$var wire 3 B alu_control [2:0] $end
$var wire 32 C a [31:0] $end
$var reg 32 D result [31:0] $end
$upscope $end
$scope module control_unit_inst $end
$var wire 3 E funct3 [2:0] $end
$var wire 7 F opcode [6:0] $end
$var wire 3 G alu_control [2:0] $end
$var reg 1 = alu_src $end
$var reg 1 < branch $end
$var reg 1 ; branch_ne $end
$var reg 1 6 jalr $end
$var reg 1 5 jump $end
$var reg 1 ) reg_write $end
$upscope $end
$scope module data_mem $end
$var wire 32 H address [31:0] $end
$var wire 1 ! clk $end
$var wire 1 " reset $end
$var wire 32 I write_data [31:0] $end
$var wire 1 2 mem_write $end
$var wire 1 4 mem_read $end
$var reg 32 J read_data [31:0] $end
$var integer 32 K i [31:0] $end
$upscope $end
$scope module decoder_unit $end
$var wire 5 L rs2 [4:0] $end
$var wire 5 M rs1 [4:0] $end
$var wire 5 N rd [4:0] $end
$var wire 7 O opcode [6:0] $end
$var wire 32 P instruction [31:0] $end
$var wire 7 Q funct7 [6:0] $end
$var wire 3 R funct3 [2:0] $end
$var reg 3 S alu_control [2:0] $end
$var reg 1 4 mem_read $end
$var reg 1 3 mem_to_reg $end
$var reg 1 2 mem_write $end
$upscope $end
$scope module imem $end
$var wire 32 T address [31:0] $end
$var reg 32 U instruction [31:0] $end
$upscope $end
$scope module imm_gen $end
$var wire 32 V instruction [31:0] $end
$var wire 7 W opcode [6:0] $end
$var reg 32 X immediate [31:0] $end
$upscope $end
$scope module pc_unit $end
$var wire 1 ! clk $end
$var wire 32 Y next_pc [31:0] $end
$var wire 1 " reset $end
$var reg 32 Z pc [31:0] $end
$upscope $end
$scope module reg_file $end
$var wire 1 ! clk $end
$var wire 5 [ rd [4:0] $end
$var wire 1 " reset $end
$var wire 5 \ rs1 [4:0] $end
$var wire 5 ] rs2 [4:0] $end
$var wire 32 ^ write_data [31:0] $end
$var wire 1 $ write_enable $end
$var reg 32 _ read_data1 [31:0] $end
$var reg 32 ` read_data2 [31:0] $end
$var integer 32 a i [31:0] $end
$upscope $end
$upscope $end
$upscope $end
$enddefinitions $end
$comment Show the parameter values. $end
$dumpall
$end
#0
$dumpvars
bx a
bx `
bx _
b0 ^
bx ]
bx \
bx [
bx Z
bx Y
bx X
bx W
bx V
bx U
bx T
b0 S
bx R
bx Q
bx P
bx O
bx N
bx M
bx L
bx K
b0 J
bx I
b0 H
b0 G
bx F
bx E
b0 D
bx C
b0 B
bx A
b0 @
bx ?
b0 >
0=
0<
0;
bx :
bx 9
bx 8
bx 7
06
05
04
03
02
b0 1
bx 0
bx /
bx .
bx -
bx ,
bx +
bx *
0)
bx (
bx '
b0 &
1%
0$
0#
1"
0!
$end
#5
b10000 &
b10000 ^
0%
b10000 >
b10000 D
b10000 H
b10000 ?
b10000 A
b0 *
b0 I
b0 `
b0 +
b0 C
b0 _
b1 @
b1 B
b1 G
b1 S
1=
1$
1)
b100 0
b100 Y
b10011 W
b0 Q
b10000 '
b10000 L
b10000 ]
b0 (
b0 M
b0 \
b0 R
b1 ,
b1 N
b1 [
b10011 O
b0 9
b0 E
b10011 /
b10011 F
b10000 :
b10000 8
b10000 X
b1000000000000000010010011 7
b1000000000000000010010011 P
b1000000000000000010010011 U
b1000000000000000010010011 V
b100 -
b0 .
b0 T
b0 Z
b100000 a
b100000000 K
1!
#10
0!
#12
0"
#15
b1000 &
b1000 ^
b10100 >
b10100 D
b10100 H
b10000 +
b10000 C
b10000 _
b1 @
b1 B
b1 G
b1 S
16
1=
1$
1)
b100 ?
b100 A
b10100 0
b10100 Y
b1100111 W
b100 '
b100 L
b100 ]
b1 (
b1 M
b1 \
b101 ,
b101 N
b101 [
b1100111 O
b1100111 /
b1100111 F
b100 8
b100 X
b10000001000001011100111 7
b10000001000001011100111 P
b10000001000001011100111 U
b10000001000001011100111 V
b1000 :
b1000 -
b100 .
b100 T
b100 Z
1!
#20
0!
#25
b11000 0
b11000 Y
1%
b0 >
b0 D
b0 H
b0 +
b0 C
b0 _
b0 @
b0 B
b0 G
b0 S
06
0=
0$
0)
b0 ?
b0 A
b0 W
b0 '
b0 L
b0 ]
b0 (
b0 M
b0 \
b0 ,
b0 N
b0 [
b0 O
b0 /
b0 F
b0 8
b0 X
b0 &
b0 ^
b0 7
b0 P
b0 U
b0 V
b10100 :
b11000 -
b10100 .
b10100 T
b10100 Z
1!
#30
0!
#35
b110111 &
b110111 ^
0%
b110111 >
b110111 D
b110111 H
b110111 ?
b110111 A
b1 @
b1 B
b1 G
b1 S
1=
1$
1)
b11100 0
b11100 Y
b10011 W
b1 Q
b10111 '
b10111 L
b10111 ]
b10 ,
b10 N
b10 [
b10011 O
b10011 /
b10011 F
b110111 8
b110111 X
b11011100000000000100010011 7
b11011100000000000100010011 P
b11011100000000000100010011 U
b11011100000000000100010011 V
b1001111 :
b11100 -
b11000 .
b11000 T
b11000 Z
1!
#40
0!
#45
b0 &
b0 ^
1%
b0 >
b0 D
b0 H
bx *
bx I
bx `
bx +
bx C
bx _
b0 @
b0 B
b0 G
b0 S
0=
0$
0)
bx ?
bx A
b100000 0
b100000 Y
bx W
bx Q
bx '
bx L
bx ]
bx (
bx M
bx \
bx R
bx ,
bx N
bx [
bx O
bx 9
bx E
bx /
bx F
bx 8
bx X
bx 7
bx P
bx U
bx V
bx :
b100000 -
b11100 .
b11100 T
b11100 Z
1!
#50
0!
#55
b100100 0
b100100 Y
b100100 -
b100000 .
b100000 T
b100000 Z
1!
#60
0!
#65
b101000 0
b101000 Y
b101000 -
b100100 .
b100100 T
b100100 Z
1!
#70
0!
#75
b101100 0
b101100 Y
b101100 -
b101000 .
b101000 T
b101000 Z
1!
#80
0!
#85
b110000 0
b110000 Y
b110000 -
b101100 .
b101100 T
b101100 Z
1!
#90
0!
#95
b110100 0
b110100 Y
b110100 -
b110000 .
b110000 T
b110000 Z
1!
#100
0!
#105
b111000 0
b111000 Y
b111000 -
b110100 .
b110100 T
b110100 Z
1!
#110
0!
#115
b111100 0
b111100 Y
b111100 -
b111000 .
b111000 T
b111000 Z
1!
#120
0!
#125
b1000000 0
b1000000 Y
b1000000 -
b111100 .
b111100 T
b111100 Z
1!
#130
0!
#135
b1000100 0
b1000100 Y
b1000100 -
b1000000 .
b1000000 T
b1000000 Z
1!
#140
0!
#145
b1001000 0
b1001000 Y
b1001000 -
b1000100 .
b1000100 T
b1000100 Z
1!
#150
0!
#155
b1001100 0
b1001100 Y
b1001100 -
b1001000 .
b1001000 T
b1001000 Z
1!
#160
0!
#165
b1010000 0
b1010000 Y
b1010000 -
b1001100 .
b1001100 T
b1001100 Z
1!
#170
0!
#175
b1010100 0
b1010100 Y
b1010100 -
b1010000 .
b1010000 T
b1010000 Z
1!
#180
0!
#185
b1011000 0
b1011000 Y
b1011000 -
b1010100 .
b1010100 T
b1010100 Z
1!
#190
0!
#195
b1011100 0
b1011100 Y
b1011100 -
b1011000 .
b1011000 T
b1011000 Z
1!
#200
0!
#205
b1100000 0
b1100000 Y
b1100000 -
b1011100 .
b1011100 T
b1011100 Z
1!
